accsyn_api/__init__.py
accsyn_api/_version.py
accsyn_api/session.py
accsyn_python_api-3.1.0.dist-info/METADATA
accsyn_python_api-3.1.0.dist-info/WHEEL
accsyn_python_api-3.1.0.dist-info/RECORD
