Metadata-Version: 2.1
Name: accsyn-python-api
Version: 3.1.0
Summary: A Python API for accsyn programmable fast and secure data delivery software
Home-page: https://accsyn.com
License: Apache-2.0
Keywords: accsyn,api,file-transfer,delivery
Author: Henrik Norin
Author-email: support@accsyn.com
Requires-Python: >=3.8,<4.0
Classifier: Development Status :: 5 - Production/Stable
Classifier: Intended Audience :: Developers
Classifier: License :: OSI Approved :: Apache Software License
Classifier: Operating System :: OS Independent
Classifier: Programming Language :: Python :: 3
Classifier: Programming Language :: Python :: 3.8
Classifier: Programming Language :: Python :: 3.9
Classifier: Programming Language :: Python :: 3.10
Classifier: Programming Language :: Python :: 3.11
Classifier: Programming Language :: Python :: 3.12
Classifier: Programming Language :: Python :: 3.13
Classifier: Topic :: Internet :: File Transfer Protocol (FTP)
Classifier: Topic :: Software Development :: Libraries :: Python Modules
Requires-Dist: requests (>=2.25.0,<3.0.0)
Project-URL: Bug Tracker, https://github.com/accsyn/accsyn-python-api/issues
Project-URL: Documentation, https://accsyn-python-api.readthedocs.io
Project-URL: Repository, https://github.com/accsyn/accsyn-python-api.git
Project-URL: Support, https://support.accsyn.com
